voiceClassifier
