Metadata-Version: 2.1
Name: voiceClassifier
Version: 1.1.2.1
Summary: A simple package for voice classifiaction
Home-page: https://github.com/Raman-Raje/voiceClassifier
Author: Raman Shinde
Author-email: raman.shinde15@gmail.com
License: MIT
Download-URL: https://github.com/Raman-Raje/voiceClassifier/archive/v_01_2.1.tar.gz
Platform: UNKNOWN
Classifier: Development Status :: 3 - Alpha
Classifier: Intended Audience :: Developers
Classifier: Topic :: Software Development :: Build Tools
Classifier: License :: OSI Approved :: MIT License
Classifier: Programming Language :: Python :: 3.5
Classifier: Programming Language :: Python :: 3.6
